Metadata-Version: 2.1
Name: dsnd-distributions-logan-lev
Version: 1.0
Summary: Gaussian and Binomial distributions
Author: Logan Levine
